{
  "subtitle": "", 
  "uuid": "2e6563f302984d099e589fa4d21b7063", 
  "language": "ben_BD", 
  "title": "\u09ae\u09cd\u09af\u09be\u09b2\u09c7\u09b0\u09bf\u09df\u09be", 
  "image": null, 
  "_version": {
    "package_version": "0.3.1", 
    "language_version": "2.7.6", 
    "language": "python", 
    "language_version_string": "2.7.6 (default, Mar 22 2014, 23:03:41) \n[GCC 4.8.2]", 
    "package": "elastic-git"
  }, 
  "slug": "what-malaria", 
  "source": null, 
  "position": 0, 
  "image_host": "http://thumbor.unicore.io", 
  "featured_in_navbar": true, 
  "id": null
}